HITphysics_curve_fit_package/__init__.py
HITphysics_curve_fit_package/crude_train.py
HITphysics_curve_fit_package/optimize.py
HITphysics_curve_fit_package/test_method.py
HITphysics_curve_fit_package/train_method.py
HITphysics_curve_fit_package/basic/J_fn.py
HITphysics_curve_fit_package/basic/__init__.py
HITphysics_curve_fit_package/basic/constants.py
HITphysics_curve_fit_package/basic/loss_fn.py
HITphysics_curve_fit_package/construct_model/__init__.py
HITphysics_curve_fit_package/construct_model/dataset.py
HITphysics_curve_fit_package/construct_model/model.py
HITphysics_curve_fit_package-0.0.dist-info/LICENSE.txt
HITphysics_curve_fit_package-0.0.dist-info/METADATA
HITphysics_curve_fit_package-0.0.dist-info/WHEEL
HITphysics_curve_fit_package-0.0.dist-info/top_level.txt
HITphysics_curve_fit_package-0.0.dist-info/RECORD
