Metadata-Version: 2.1
Name: HITphysics-curve-fit-package
Version: 0.0
Summary: A self-used package for curve fitting
Home-page: 
Author: Shangjing Liu
Author-email: 2022110002@stu.hit.edu.cn
Classifier: Programming Language :: Python :: 3
Classifier: License :: OSI Approved :: MIT License
Classifier: Operating System :: OS Independent
License-File: LICENSE.txt
Requires-Dist: torch
Requires-Dist: numpy
Requires-Dist: matplotlib
Requires-Dist: simpy
